vtdecode/__init__.py
vtdecode/main.py
vtdecode/mapbox.py
vtdecode/mapillary.py
vtdecode/decoder/BytesDecoder.py
vtdecode/decoder/FileDecoder.py
vtdecode/decoder/LayerDecoder.py
vtdecode/decoder/__init__.py
vtdecode/decoder/decode.py
vtdecode/decoder/utils.py
vtdecode/decoder/vector_tile_pb2.py
vtdecode-1.2.5.dist-info/LICENSE
vtdecode-1.2.5.dist-info/METADATA
vtdecode-1.2.5.dist-info/WHEEL
vtdecode-1.2.5.dist-info/entry_points.txt
vtdecode-1.2.5.dist-info/top_level.txt
vtdecode-1.2.5.dist-info/RECORD
