Metadata-Version: 2.1
Name: vtdecode
Version: 1.2.5
Summary: Fetch and decode vector tiles
Author-email: Metric-Void <metricvoidlx@gmail.com>
License: MIT
Project-URL: Homepage, https://github.com/Metric-Void/vtdecode
Keywords: vector tile,mapbox,mapillary
Classifier: License :: OSI Approved :: MIT License
Classifier: Programming Language :: Python
Classifier: Programming Language :: Python :: 3
Requires-Python: >=3.8
License-File: LICENSE
Requires-Dist: protobuf (>=4.21.1)
Requires-Dist: geojson (>=2.5.0)
Requires-Dist: aiohttp (>=3.8.1)
Requires-Dist: aiohttp-retry (>=2.4.6)
Requires-Dist: pyparsing (>=3.0.4)
